tox_venv/__init__.py
tox_venv/hooks.py
tox_venv-0.4.0.dist-info/LICENSE
tox_venv-0.4.0.dist-info/METADATA
tox_venv-0.4.0.dist-info/WHEEL
tox_venv-0.4.0.dist-info/entry_points.txt
tox_venv-0.4.0.dist-info/top_level.txt
tox_venv-0.4.0.dist-info/RECORD
